<PAMDataset>
  <Metadata>
    <MDI key="DataType">Generic</MDI>
  </Metadata>
  <Metadata domain="Esri">
    <MDI key="PyramidResamplingType">NEAREST</MDI>
  </Metadata>
  <PAMRasterBand band="1">
    <Histograms>
      <HistItem>
        <HistMin>0.1212111189961433</HistMin>
        <HistMax>5.587352752685547</HistMax>
        <BucketCount>256</BucketCount>
        <IncludeOutOfRange>1</IncludeOutOfRange>
        <Approximate>0</Approximate>
        <HistCounts>7|4|8|17|13|10|13|16|29|18|30|52|101|172|199|212|284|340|383|384|459|518|765|826|1105|1148|1045|1181|1053|942|872|928|1143|1194|1229|1171|1195|1191|1368|1548|1397|1519|1666|1297|1166|966|796|736|661|669|625|624|698|786|797|814|1076|1522|934|875|698|619|578|522|515|512|524|508|520|482|576|529|516|475|484|405|356|269|292|276|225|248|263|224|206|267|251|220|195|136|136|146|126|113|90|101|105|83|67|84|75|81|87|86|113|89|78|96|99|72|86|71|79|96|87|76|71|101|65|63|79|81|59|72|81|77|66|56|67|55|68|59|48|57|61|45|56|49|50|59|47|47|64|49|55|52|43|57|67|60|45|46|46|49|51|36|34|48|54|38|48|41|35|45|28|39|49|52|47|42|55|54|53|43|54|49|51|71|102|88|89|89|147|158|154|219|229|726|364|189|133|184|125|141|132|160|138|93|67|78|59|72|49|39|47|66|46|46|34|39|34|24|37|40|32|39|26|8|6|3|11|8|12|17|15|11|11|7|11|3|11|11|5|7|8|17|5|5|10|9|12|11|4|6|5|9|4|5|10|5|3|5|5|7|5|1</HistCounts>
      </HistItem>
    </Histograms>
    <Metadata>
      <MDI key="RepresentationType">ATHEMATIC</MDI>
      <MDI key="STATISTICS_COVARIANCES">1.018828667004649</MDI>
      <MDI key="STATISTICS_MAXIMUM">5.5873527526855</MDI>
      <MDI key="STATISTICS_MEAN">1.494107749024</MDI>
      <MDI key="STATISTICS_MINIMUM">0.12121111899614</MDI>
      <MDI key="STATISTICS_SKIPFACTORX">1</MDI>
      <MDI key="STATISTICS_SKIPFACTORY">1</MDI>
      <MDI key="STATISTICS_STDDEV">1.0093704310136</MDI>
    </Metadata>
  </PAMRasterBand>
</PAMDataset>
